CHANGES.rst
CONTRIBUTORS.rst
MANIFEST.in
README.rst
pyproject.toml
setup.cfg
setup.py
docs/LICENSE.GPL
docs/LICENSE.rst
docs/index.rst
src/liege/__init__.py
src/liege.urban.egg-info/PKG-INFO
src/liege.urban.egg-info/SOURCES.txt
src/liege.urban.egg-info/dependency_links.txt
src/liege.urban.egg-info/entry_points.txt
src/liege.urban.egg-info/namespace_packages.txt
src/liege.urban.egg-info/not-zip-safe
src/liege.urban.egg-info/requires.txt
src/liege.urban.egg-info/top_level.txt
src/liege/urban/__init__.py
src/liege/urban/config.py
src/liege/urban/configure.zcml
src/liege/urban/indexes.py
src/liege/urban/indexes.zcml
src/liege/urban/interfaces.py
src/liege/urban/interfaces.zcml
src/liege/urban/licence_fields_permissions.py
src/liege/urban/overrides.zcml
src/liege/urban/permissions.zcml
src/liege/urban/setuphandlers.py
src/liege/urban/skins.zcml
src/liege/urban/testing.py
src/liege/urban/testing.zcml
src/liege/urban/vocabulary.py
src/liege/urban/vocabulary.zcml
src/liege/urban/Extensions/catalog_stats.py
src/liege/urban/Extensions/close_env_licences.py
src/liege/urban/Extensions/close_old_tasks.py
src/liege/urban/Extensions/event_portaltype_update.py
src/liege/urban/Extensions/fix_127.py
src/liege/urban/Extensions/fix_borderinglicences_state.py
src/liege/urban/Extensions/fix_categorytownship.py
src/liege/urban/Extensions/fix_decision.py
src/liege/urban/Extensions/fix_decisions_dates.py
src/liege/urban/Extensions/fix_preliminarynotice_state.py
src/liege/urban/Extensions/import_architects.py
src/liege/urban/Extensions/import_notaries.py
src/liege/urban/Extensions/merge_configs.py
src/liege/urban/Extensions/merge_foldermanager_config.py
src/liege/urban/Extensions/missing_events_config.py
src/liege/urban/Extensions/suspension_update.py
src/liege/urban/Extensions/update_schedule_config.py
src/liege/urban/Extensions/update_task_configs.py
src/liege/urban/actionspanel/__init__.py
src/liege/urban/actionspanel/configure.zcml
src/liege/urban/actionspanel/urbandoc_actions.py
src/liege/urban/adapters/__init__.py
src/liege/urban/adapters/configure.zcml
src/liege/urban/adapters/is_archive.py
src/liege/urban/adapters/shore.py
src/liege/urban/adapters/urbain220.py
src/liege/urban/browser/__init__.py
src/liege/urban/browser/activity_report.py
src/liege/urban/browser/address_search.py
