Metadata-Version: 2.1
Name: liege.urban
Version: 1.0.10
Summary: Liège urban profile
Home-page: https://pypi.python.org/pypi/liege.urban
Author: Simon Delcourt
Author-email: simon.delcourt@imio.be
License: GPL version 2
Keywords: Python Plone
Classifier: Environment :: Web Environment
Classifier: Framework :: Plone
Classifier: Framework :: Plone :: 4.3
Classifier: Programming Language :: Python
Classifier: Programming Language :: Python :: 2.7
Classifier: Operating System :: OS Independent
Classifier: License :: OSI Approved :: GNU General Public License v2 (GPLv2)
Provides-Extra: test
Provides-Extra: pytest
